agin/__init__.py
agin/classification/__init__.py
agin/classification/decision_tree_classifier.py
agin/classification/knn_classifier.py
agin/classification/linear_svm.py
agin/classification/logistic_regression.py
agin/classification/naive_bayes.py
agin/classification/nonlinear_svm.py
agin/classification/random_forest_classifier.py
agin/neural_network/__init__.py
agin/neural_network/neural_network.py
agin/preprocessing/__init__.py
agin/preprocessing/minmax.py
agin/regression/__init__.py
agin/regression/decision_tree_regressor.py
agin/regression/elastic_net_regression.py
agin/regression/knn_regressor.py
agin/regression/lasso_regression.py
agin/regression/linear_regression.py
agin/regression/multilinear_regression.py
agin/regression/polynomial_regression.py
agin/regression/random_forest_regressor.py
agin/regression/ridge_regression.py
agin/utils/__init__.py
agin/utils/health.py
agin/utils/neuron.py
agin/utils/node.py
AginPy-1.0.0.dist-info/LICENSE
AginPy-1.0.0.dist-info/METADATA
AginPy-1.0.0.dist-info/WHEEL
AginPy-1.0.0.dist-info/top_level.txt
AginPy-1.0.0.dist-info/RECORD
