Metadata-Version: 2.1
Name: AginPy
Version: 1.0.0
Summary: A one-stop machine learning solution
Author-email: Agnik Bakshi <bakshi.agnik@gmail.com>, Indranjana Chatterjee <indranjanachatterjee@gmail.com>
Project-URL: Homepage, https://agnik7.github.io/Agin/
Classifier: Programming Language :: Python :: 3
Classifier: License :: OSI Approved :: GNU General Public License v3 (GPLv3)
Classifier: Operating System :: OS Independent
Requires-Python: >=3.8
License-File: LICENSE
Requires-Dist: numpy
Requires-Dist: pandas
